{
  "Team 1": [
    {
      "adp": 1,
      "name": "Ja'Marr Chase",
      "pos": "WR",
      "team": "CIN",
      "pick": 1
    },
    {
      "adp": 24,
      "name": "Bucky Irving",
      "pos": "RB",
      "team": "TB",
      "pick": 1
    },
    {
      "adp": 25,
      "name": "Kyren Williams",
      "pos": "RB",
      "team": "LAR",
      "pick": 1
    },
    {
      "adp": 48,
      "name": "DK Metcalf",
      "pos": "WR",
      "team": "PIT",
      "pick": 1
    },
    {
      "adp": 49,
      "name": "Patrick Mahomes",
      "pos": "QB",
      "team": "KC",
      "pick": 1
    },
    {
      "adp": 73,
      "name": "Mark Andrews",
      "pos": "TE",
      "team": "BAL",
      "pick": 1
    },
    {
      "adp": 74,
      "name": "Jerry Jeudy",
      "pos": "WR",
      "team": "CLE",
      "pick": 1
    },
    {
      "adp": 97,
      "name": "Cam Skattebo",
      "pos": "RB",
      "team": "NYG",
      "pick": 1
    },
    {
      "adp": 98,
      "name": "J.K. Dobbins",
      "pos": "RB",
      "team": "DEN",
      "pick": 1
    },
    {
      "adp": 125,
      "name": "Dalton Kincaid",
      "pos": "TE",
      "team": "BUF",
      "pick": 1
    },
    {
      "adp": 127,
      "name": "C.J. Stroud",
      "pos": "QB",
      "team": "HOU",
      "pick": 1
    }
  ],
  "Team 2": [
    {
      "adp": 2,
      "name": "Bijan Robinson",
      "pos": "RB",
      "team": "ATL",
      "pick": 2
    },
    {
      "adp": 23,
      "name": "Lamar Jackson",
      "pos": "QB",
      "team": "BAL",
      "pick": 2
    },
    {
      "adp": 26,
      "name": "Ladd McConkey",
      "pos": "WR",
      "team": "LAC",
      "pick": 2
    },
    {
      "adp": 47,
      "name": "James Conner",
      "pos": "RB",
      "team": "ARI",
      "pick": 2
    },
    {
      "adp": 50,
      "name": "DJ Moore",
      "pos": "WR",
      "team": "BUF",
      "pick": 2
    },
    {
      "adp": 72,
      "name": "Jaylen Waddle",
      "pos": "WR",
      "team": "MIA",
      "pick": 2
    },
    {
      "adp": 75,
      "name": "Tyrone Tracy Jr.",
      "pos": "RB",
      "team": "NYG",
      "pick": 2
    },
    {
      "adp": 96,
      "name": "Jacory Croskey-Merritt",
      "pos": "RB",
      "team": "WAS",
      "pick": 2
    },
    {
      "adp": 100,
      "name": "Jared Goff",
      "pos": "QB",
      "team": "DET",
      "pick": 2
    },
    {
      "adp": 124,
      "name": "Jayden Reed",
      "pos": "WR",
      "team": "GB",
      "pick": 2
    },
    {
      "adp": 130,
      "name": "Najee Harris",
      "pos": "RB",
      "team": "LAC",
      "pick": 2
    }
  ],
  "Team 3": [
    {
      "adp": 3,
      "name": "Saquon Barkley",
      "pos": "RB",
      "team": "PHI",
      "pick": 3
    },
    {
      "adp": 22,
      "name": "Chase Brown",
      "pos": "RB",
      "team": "CIN",
      "pick": 3
    },
    {
      "adp": 27,
      "name": "Trey McBride",
      "pos": "TE",
      "team": "ARI",
      "pick": 3
    },
    {
      "adp": 46,
      "name": "Chuba Hubbard",
      "pos": "RB",
      "team": "CAR",
      "pick": 3
    },
    {
      "adp": 51,
      "name": "Courtland Sutton",
      "pos": "WR",
      "team": "DEN",
      "pick": 3
    },
    {
      "adp": 71,
      "name": "Rashee Rice",
      "pos": "WR",
      "team": "KC",
      "pick": 3
    },
    {
      "adp": 76,
      "name": "Kaleb Johnson",
      "pos": "RB",
      "team": "PIT",
      "pick": 3
    },
    {
      "adp": 95,
      "name": "Jordan Mason",
      "pos": "RB",
      "team": "MIN",
      "pick": 3
    },
    {
      "adp": 101,
      "name": "Khalil Shakir",
      "pos": "WR",
      "team": "BUF",
      "pick": 3
    },
    {
      "adp": 123,
      "name": "Drake Maye",
      "pos": "QB",
      "team": "NE",
      "pick": 3
    },
    {
      "adp": 131,
      "name": "Tank Bigsby",
      "pos": "RB",
      "team": "PHI",
      "pick": 3
    }
  ],
  "Team 4": [
    {
      "adp": 4,
      "name": "Jahmyr Gibbs",
      "pos": "RB",
      "team": "DET",
      "pick": 4
    },
    {
      "adp": 21,
      "name": "A.J. Brown",
      "pos": "WR",
      "team": "PHI",
      "pick": 4
    },
    {
      "adp": 28,
      "name": "James Cook",
      "pos": "RB",
      "team": "BUF",
      "pick": 4
    },
    {
      "adp": 45,
      "name": "TreVeyon Henderson",
      "pos": "RB",
      "team": "NE",
      "pick": 4
    },
    {
      "adp": 52,
      "name": "Sam LaPorta",
      "pos": "TE",
      "team": "DET",
      "pick": 4
    },
    {
      "adp": 70,
      "name": "Bo Nix",
      "pos": "QB",
      "team": "DEN",
      "pick": 4
    },
    {
      "adp": 77,
      "name": "Rome Odunze",
      "pos": "WR",
      "team": "CHI",
      "pick": 4
    },
    {
      "adp": 94,
      "name": "Dak Prescott",
      "pos": "QB",
      "team": "DAL",
      "pick": 4
    },
    {
      "adp": 102,
      "name": "Chris Godwin",
      "pos": "WR",
      "team": "TB",
      "pick": 4
    },
    {
      "adp": 122,
      "name": "Nick Chubb",
      "pos": "RB",
      "team": "CLE",
      "pick": 4
    },
    {
      "adp": 132,
      "name": "Kyle Pitts",
      "pos": "TE",
      "team": "ATL",
      "pick": 4
    }
  ],
  "Team 5": [
    {
      "adp": 5,
      "name": "CeeDee Lamb",
      "pos": "WR",
      "team": "DAL",
      "pick": 5
    },
    {
      "adp": 20,
      "name": "Josh Allen",
      "pos": "QB",
      "team": "BUF",
      "pick": 5
    },
    {
      "adp": 29,
      "name": "Jayden Daniels",
      "pos": "QB",
      "team": "WAS",
      "pick": 5
    },
    {
      "adp": 44,
      "name": "Marvin Harrison Jr.",
      "pos": "WR",
      "team": "ARI",
      "pick": 5
    },
    {
      "adp": 53,
      "name": "Xavier Worthy",
      "pos": "WR",
      "team": "KC",
      "pick": 5
    },
    {
      "adp": 69,
      "name": "Travis Hunter",
      "pos": "WR",
      "team": "JAC",
      "pick": 5
    },
    {
      "adp": 78,
      "name": "Chris Olave",
      "pos": "WR",
      "team": "NO",
      "pick": 5
    },
    {
      "adp": 93,
      "name": "Brock Purdy",
      "pos": "QB",
      "team": "SF",
      "pick": 5
    },
    {
      "adp": 104,
      "name": "Jauan Jennings",
      "pos": "WR",
      "team": "SF",
      "pick": 5
    },
    {
      "adp": 121,
      "name": "Josh Downs",
      "pos": "WR",
      "team": "IND",
      "pick": 5
    },
    {
      "adp": 133,
      "name": "Jordan Love",
      "pos": "QB",
      "team": "GB",
      "pick": 5
    }
  ],
  "Team 6": [
    {
      "adp": 6,
      "name": "Justin Jefferson",
      "pos": "WR",
      "team": "MIN",
      "pick": 6
    },
    {
      "adp": 19,
      "name": "Brock Bowers",
      "pos": "TE",
      "team": "LV",
      "pick": 6
    },
    {
      "adp": 30,
      "name": "Tee Higgins",
      "pos": "WR",
      "team": "CIN",
      "pick": 6
    },
    {
      "adp": 43,
      "name": "Kenneth Walker III",
      "pos": "RB",
      "team": "KC",
      "pick": 6
    },
    {
      "adp": 54,
      "name": "D'Andre Swift",
      "pos": "RB",
      "team": "CHI",
      "pick": 6
    },
    {
      "adp": 68,
      "name": "George Pickens",
      "pos": "WR",
      "team": "DAL",
      "pick": 6
    },
    {
      "adp": 79,
      "name": "Deebo Samuel",
      "pos": "WR",
      "team": "SF",
      "pick": 6
    },
    {
      "adp": 92,
      "name": "Travis Etienne",
      "pos": "RB",
      "team": "NO",
      "pick": 6
    },
    {
      "adp": 105,
      "name": "Zach Charbonnet",
      "pos": "RB",
      "team": "SEA",
      "pick": 6
    },
    {
      "adp": 120,
      "name": "Brian Robinson Jr.",
      "pos": "RB",
      "team": "WSH",
      "pick": 6
    },
    {
      "adp": 135,
      "name": "Braelon Allen",
      "pos": "RB",
      "team": "NYJ",
      "pick": 6
    }
  ],
  "Team 7": [
    {
      "adp": 7,
      "name": "Christian McCaffrey",
      "pos": "RB",
      "team": "SF",
      "pick": 7
    },
    {
      "adp": 18,
      "name": "Jonathan Taylor",
      "pos": "RB",
      "team": "IND",
      "pick": 7
    },
    {
      "adp": 31,
      "name": "Tyreek Hill",
      "pos": "WR",
      "team": "MIA",
      "pick": 7
    },
    {
      "adp": 42,
      "name": "Davante Adams",
      "pos": "WR",
      "team": "LAR",
      "pick": 7
    },
    {
      "adp": 55,
      "name": "DeVonta Smith",
      "pos": "WR",
      "team": "PHI",
      "pick": 7
    },
    {
      "adp": 67,
      "name": "Aaron Jones",
      "pos": "RB",
      "team": "MIN",
      "pick": 7
    },
    {
      "adp": 80,
      "name": "David Njoku",
      "pos": "TE",
      "team": "CLE",
      "pick": 7
    },
    {
      "adp": 91,
      "name": "Jordan Addison",
      "pos": "WR",
      "team": "MIN",
      "pick": 7
    },
    {
      "adp": 106,
      "name": "Tucker Kraft",
      "pos": "TE",
      "team": "GB",
      "pick": 7
    },
    {
      "adp": 119,
      "name": "Caleb Williams",
      "pos": "QB",
      "team": "CHI",
      "pick": 7
    },
    {
      "adp": 136,
      "name": "Jake Ferguson",
      "pos": "TE",
      "team": "DAL",
      "pick": 7
    },
    {
      "adp": 150,
      "name": "Jayden Higgins",
      "pos": "WR",
      "team": "HOU",
      "pick": 7
    }
  ],
  "Team 8": [
    {
      "adp": 8,
      "name": "Malik Nabers",
      "pos": "WR",
      "team": "NYG",
      "pick": 8
    },
    {
      "adp": 17,
      "name": "Drake London",
      "pos": "WR",
      "team": "ATL",
      "pick": 8
    },
    {
      "adp": 32,
      "name": "Joe Burrow",
      "pos": "QB",
      "team": "CIN",
      "pick": 8
    },
    {
      "adp": 41,
      "name": "Garrett Wilson",
      "pos": "WR",
      "team": "NYJ",
      "pick": 8
    },
    {
      "adp": 56,
      "name": "Tetairoa McMillan",
      "pos": "WR",
      "team": "CAR",
      "pick": 8
    },
    {
      "adp": 66,
      "name": "Tony Pollard",
      "pos": "RB",
      "team": "TEN",
      "pick": 8
    },
    {
      "adp": 81,
      "name": "Evan Engram",
      "pos": "TE",
      "team": "DEN",
      "pick": 8
    },
    {
      "adp": 90,
      "name": "Cooper Kupp",
      "pos": "WR",
      "team": "SEA",
      "pick": 8
    },
    {
      "adp": 107,
      "name": "Javonte Williams",
      "pos": "RB",
      "team": "DAL",
      "pick": 8
    },
    {
      "adp": 118,
      "name": "Quinshon Judkins",
      "pos": "RB",
      "team": "CLE",
      "pick": 8
    },
    {
      "adp": 137,
      "name": "Darnell Mooney",
      "pos": "WR",
      "team": "TEN",
      "pick": 8
    },
    {
      "adp": 149,
      "name": "Christian Kirk",
      "pos": "WR",
      "team": "JAC",
      "pick": 8
    }
  ],
  "Team 9": [
    {
      "adp": 9,
      "name": "Amon-Ra St. Brown",
      "pos": "WR",
      "team": "DET",
      "pick": 9
    },
    {
      "adp": 16,
      "name": "Josh Jacobs",
      "pos": "RB",
      "team": "GB",
      "pick": 9
    },
    {
      "adp": 33,
      "name": "Jaxon Smith-Njigba",
      "pos": "WR",
      "team": "SEA",
      "pick": 9
    },
    {
      "adp": 40,
      "name": "Mike Evans",
      "pos": "WR",
      "team": "TB",
      "pick": 9
    },
    {
      "adp": 57,
      "name": "Jameson Williams",
      "pos": "WR",
      "team": "DET",
      "pick": 9
    },
    {
      "adp": 65,
      "name": "Calvin Ridley",
      "pos": "WR",
      "team": "TEN",
      "pick": 9
    },
    {
      "adp": 82,
      "name": "Emeka Egbuka",
      "pos": "WR",
      "team": "TB",
      "pick": 9
    },
    {
      "adp": 89,
      "name": "Matthew Golden",
      "pos": "WR",
      "team": "GB",
      "pick": 9
    },
    {
      "adp": 108,
      "name": "Michael Pittman Jr.",
      "pos": "WR",
      "team": "PIT",
      "pick": 9
    },
    {
      "adp": 116,
      "name": "Keon Coleman",
      "pos": "WR",
      "team": "BUF",
      "pick": 9
    },
    {
      "adp": 139,
      "name": "Jaydon Blue",
      "pos": "RB",
      "team": "DAL",
      "pick": 9
    },
    {
      "adp": 148,
      "name": "Bhayshul Tuten",
      "pos": "RB",
      "team": "JAC",
      "pick": 9
    }
  ],
  "Team 10": [
    {
      "adp": 10,
      "name": "Derrick Henry",
      "pos": "RB",
      "team": "BAL",
      "pick": 10
    },
    {
      "adp": 15,
      "name": "Brian Thomas Jr.",
      "pos": "WR",
      "team": "JAC",
      "pick": 10
    },
    {
      "adp": 34,
      "name": "Jalen Hurts",
      "pos": "QB",
      "team": "PHI",
      "pick": 10
    },
    {
      "adp": 39,
      "name": "Terry McLaurin",
      "pos": "WR",
      "team": "WAS",
      "pick": 10
    },
    {
      "adp": 58,
      "name": "David Montgomery",
      "pos": "RB",
      "team": "HOU",
      "pick": 10
    },
    {
      "adp": 64,
      "name": "T.J. Hockenson",
      "pos": "TE",
      "team": "MIN",
      "pick": 10
    },
    {
      "adp": 83,
      "name": "Kyler Murray",
      "pos": "QB",
      "team": "ARI",
      "pick": 10
    },
    {
      "adp": 88,
      "name": "Jakobi Meyers",
      "pos": "WR",
      "team": "JAC",
      "pick": 10
    },
    {
      "adp": 109,
      "name": "Austin Ekeler",
      "pos": "RB",
      "team": "WSH",
      "pick": 10
    },
    {
      "adp": 115,
      "name": "Joe Mixon",
      "pos": "RB",
      "team": "HOU",
      "pick": 10
    },
    {
      "adp": 140,
      "name": "Dallas Goedert",
      "pos": "TE",
      "team": "PHI",
      "pick": 10
    },
    {
      "adp": 147,
      "name": "Brandon Aiyuk",
      "pos": "WR",
      "team": "SF",
      "pick": 10
    }
  ],
  "Team 11": [
    {
      "adp": 11,
      "name": "Ashton Jeanty",
      "pos": "RB",
      "team": "LV",
      "pick": 11
    },
    {
      "adp": 14,
      "name": "De'Von Achane",
      "pos": "RB",
      "team": "MIA",
      "pick": 11
    },
    {
      "adp": 35,
      "name": "Omarion Hampton",
      "pos": "RB",
      "team": "LAC",
      "pick": 11
    },
    {
      "adp": 38,
      "name": "Breece Hall",
      "pos": "RB",
      "team": "NYJ",
      "pick": 11
    },
    {
      "adp": 59,
      "name": "RJ Harvey",
      "pos": "RB",
      "team": "DEN",
      "pick": 11
    },
    {
      "adp": 62,
      "name": "Baker Mayfield",
      "pos": "QB",
      "team": "TB",
      "pick": 11
    },
    {
      "adp": 84,
      "name": "Jaylen Warren",
      "pos": "RB",
      "team": "PIT",
      "pick": 11
    },
    {
      "adp": 87,
      "name": "Tyler Warren",
      "pos": "TE",
      "team": "IND",
      "pick": 11
    },
    {
      "adp": 110,
      "name": "Justin Herbert",
      "pos": "QB",
      "team": "LAC",
      "pick": 11
    },
    {
      "adp": 114,
      "name": "Justin Fields",
      "pos": "QB",
      "team": "NYJ",
      "pick": 11
    },
    {
      "adp": 142,
      "name": "Rashid Shaheed",
      "pos": "WR",
      "team": "SEA",
      "pick": 11
    },
    {
      "adp": 146,
      "name": "Keenan Allen",
      "pos": "WR",
      "team": "LAC",
      "pick": 11
    }
  ],
  "Team 12": [
    {
      "adp": 12,
      "name": "Puka Nacua",
      "pos": "WR",
      "team": "LAR",
      "pick": 12
    },
    {
      "adp": 13,
      "name": "Nico Collins",
      "pos": "WR",
      "team": "HOU",
      "pick": 12
    },
    {
      "adp": 36,
      "name": "Alvin Kamara",
      "pos": "RB",
      "team": "NO",
      "pick": 12
    },
    {
      "adp": 37,
      "name": "George Kittle",
      "pos": "TE",
      "team": "SF",
      "pick": 12
    },
    {
      "adp": 60,
      "name": "Isiah Pacheco",
      "pos": "RB",
      "team": "DET",
      "pick": 12
    },
    {
      "adp": 61,
      "name": "Zay Flowers",
      "pos": "WR",
      "team": "BAL",
      "pick": 12
    },
    {
      "adp": 85,
      "name": "Ricky Pearsall",
      "pos": "WR",
      "team": "SF",
      "pick": 12
    },
    {
      "adp": 86,
      "name": "Stefon Diggs",
      "pos": "WR",
      "team": "NE",
      "pick": 12
    },
    {
      "adp": 111,
      "name": "Rhamondre Stevenson",
      "pos": "RB",
      "team": "NE",
      "pick": 12
    },
    {
      "adp": 113,
      "name": "Colston Loveland",
      "pos": "TE",
      "team": "CHI",
      "pick": 12
    },
    {
      "adp": 143,
      "name": "Rachaad White",
      "pos": "RB",
      "team": "TB",
      "pick": 12
    },
    {
      "adp": 145,
      "name": "J.J. McCarthy",
      "pos": "QB",
      "team": "MIN",
      "pick": 12
    }
  ]
}