{
  "trade_id": "hill_vs_diggs_2026",
  "created_at": "2026-03-19T18:56:21.714249Z",
  "context": {
    "league_type": "dynasty",
    "scoring": "PPR",
    "team_a_context": {
      "mode": "contender"
    },
    "team_b_context": {
      "mode": "rebuild"
    }
  },
  "steps": [
    {
      "step": 1,
      "team_a_offers": [
        {
          "player": "Tyreek Hill",
          "ktc_value": 7500,
          "position": "WR",
          "age": 31,
          "asset_type": "player"
        }
      ],
      "team_b_offers": [
        {
          "player": "Stefon Diggs",
          "ktc_value": 3500,
          "position": "WR",
          "age": 32,
          "asset_type": "player"
        }
      ],
      "team_a_total_value": 7500,
      "team_b_total_value": 3500,
      "value_difference": 4000,
      "outcome": "team_a_wins",
      "reasoning": "Hill still elite at 31. Diggs 32 and on the decline. Both Puka-aged WR but Hill clearly better."
    }
  ]
}